cyclotron/__init__.py
cyclotron/router.py
cyclotron/rx.py
cyclotron/asyncio/__init__.py
cyclotron/asyncio/runner.py
cyclotron/asyncio/stop.py
cyclotron/backpressure/__init__.py
cyclotron/backpressure/pid.py
cyclotron/debug/__init__.py
cyclotron/debug/trace.py
cyclotron-2.0.1.dist-info/LICENSE.txt
cyclotron-2.0.1.dist-info/METADATA
cyclotron-2.0.1.dist-info/WHEEL
cyclotron-2.0.1.dist-info/top_level.txt
cyclotron-2.0.1.dist-info/RECORD
