Metadata-Version: 2.1
Name: cyclotron
Version: 2.0.1
Summary: A reactive stream cycle implementation in python
Author: Romain Picard
Author-email: romain.picard@oakbits.com
License: Copyright (c) 2018 by Romain Picard
Project-URL: repository, https://github.com/MainRo/cyclotron-py.git
Project-URL: documentation, https://cyclotron-py.readthedocs.io
Keywords: reactivex,cyclejs
Classifier: Development Status :: 5 - Production/Stable
Classifier: Intended Audience :: Developers
Classifier: Programming Language :: Python :: 3
Requires-Python: >=3.7
License-File: LICENSE.txt
Requires-Dist: reactivex (~=4.0)
Provides-Extra: test
Requires-Dist: pytest ; extra == 'test'
